tiny_notepad/__init__.py
tiny_notepad/main.py
tiny_notepad-0.1.4.dist-info/licenses/LICENSE
tiny_notepad-0.1.4.dist-info/METADATA
tiny_notepad-0.1.4.dist-info/WHEEL
tiny_notepad-0.1.4.dist-info/entry_points.txt
tiny_notepad-0.1.4.dist-info/top_level.txt
tiny_notepad-0.1.4.dist-info/RECORD
