Metadata-Version: 2.4
Name: tiny_notepad
Version: 0.1.4
Summary: A minimal notepad with Ollama integration
Home-page: https://github.com/ronxldwilson/tiny_notepad
Author: Ronald Wilson
Classifier: Programming Language :: Python :: 3
Classifier: Operating System :: OS Independent
Requires-Python: >=3.7
License-File: LICENSE
Requires-Dist: requests
Dynamic: author
Dynamic: classifier
Dynamic: description
Dynamic: description-content-type
Dynamic: home-page
Dynamic: license-file
Dynamic: requires-dist
Dynamic: requires-python
Dynamic: summary
